hemlock_cli/__init__.py
hemlock_cli/add_profile.py
hemlock_cli/content.sh
hemlock_cli/deploy.sh
hemlock_cli/hlk.py
hemlock_cli/hlk.sh
hemlock_cli/init.sh
hemlock_cli/setup.sh
hemlock_cli/update_requirements.py
hemlock_cli/env/export_yaml.py
hemlock_cli/env/update_yaml.py
hemlock_cli/gcloud/cors.json
hemlock_cli/gcloud/create_cors.py
hemlock_cli/gcloud/gen_id.py
hemlock_cli/setup/add_to_path.py
hemlock_cli-0.0.21.dist-info/LICENSE
hemlock_cli-0.0.21.dist-info/METADATA
hemlock_cli-0.0.21.dist-info/WHEEL
hemlock_cli-0.0.21.dist-info/entry_points.txt
hemlock_cli-0.0.21.dist-info/top_level.txt
hemlock_cli-0.0.21.dist-info/RECORD
