Metadata-Version: 2.1
Name: hemlock-cli
Version: 0.0.21
Summary: Command line interface for hemlock projects
Home-page: https://dsbowen.github.io/hemlock
Author: Dillon Bowen
Author-email: dsbowen@wharton.upenn.edu
License: UNKNOWN
Platform: UNKNOWN
Classifier: Programming Language :: Python :: 3
Classifier: License :: OSI Approved :: MIT License
Classifier: Operating System :: OS Independent
Requires-Python: >=3.6
Requires-Dist: click (>=7.0)
